stackoperator/__init__.py
stackoperator/batchOperator.py
stackoperator/cfnReader.py
stackoperator/readerFactory.py
stackoperator/resourcegroupReader.py
stackoperator/tfReader.py
stackoperator-0.2.0.dist-info/METADATA
stackoperator-0.2.0.dist-info/WHEEL
stackoperator-0.2.0.dist-info/entry_points.txt
stackoperator-0.2.0.dist-info/top_level.txt
stackoperator-0.2.0.dist-info/RECORD
