Metadata-Version: 2.1
Name: stackoperator
Version: 0.2.0
Summary: A small utility to help do start, stop and tag actions in an IaC stack for cost optimization purpose.
Author-email: Henry Huo <happy78@live.com>
Classifier: Programming Language :: Python :: 3
Classifier: License :: OSI Approved :: GNU General Public License v3 or later (GPLv3+)
Classifier: Operating System :: OS Independent
Requires-Python: >=3.7
Requires-Dist: boto3
